seqdata/__init__.py
seqdata/_io/__init__.py
seqdata/_io/bed_ops.py
seqdata/_io/read.py
seqdata/_io/readers/__init__.py
seqdata/_io/readers/bam.py
seqdata/_io/readers/fasta.py
seqdata/_io/readers/table.py
seqdata/_io/readers/vcf.py
seqdata/_io/readers/wig.py
seqdata/_io/readers.py
seqdata/_io/utils.py
seqdata/datasets.py
seqdata/torch.py
seqdata/types.py
seqdata/xarray/seqdata.py
seqdata/xarray/utils.py
seqdata-0.2.2.dist-info/LICENSE
seqdata-0.2.2.dist-info/METADATA
seqdata-0.2.2.dist-info/WHEEL
seqdata-0.2.2.dist-info/RECORD
