Metadata-Version: 2.1
Name: seqdata
Version: 0.2.2
Summary: Annotated sequence data
Author: David Laub
Author-email: dlaub@ucsd.edu
Requires-Python: >=3.9
Classifier: Programming Language :: Python :: 3
Classifier: Programming Language :: Python :: 3.9
Classifier: Programming Language :: Python :: 3.10
Classifier: Programming Language :: Python :: 3.11
Classifier: Programming Language :: Python :: 3.12
Classifier: Programming Language :: Python :: 3.13
Provides-Extra: torch
Requires-Dist: cyvcf2 (>=0.30.18,<0.31.0)
Requires-Dist: dask (>=2023.3.2,<2024.0.0)
Requires-Dist: joblib (>=1.1.0,<2.0.0)
Requires-Dist: more-itertools (>=9.1.0,<10.0.0)
Requires-Dist: natsort (>=8.3.1,<9.0.0)
Requires-Dist: numcodecs (>=0.11.0,<0.12.0)
Requires-Dist: numpy (>=1.26,<2.0)
Requires-Dist: pandas (>=1.5.2,<2.0.0)
Requires-Dist: pandera[polars] (>=0.22.0,<0.23.0)
Requires-Dist: polars (>=1.0.0,<2.0.0)
Requires-Dist: pooch (>=1.8.2,<2.0.0)
Requires-Dist: pyBigWig (>=0.3.22,<0.4.0)
Requires-Dist: pyarrow (>=17.0.0,<18.0.0)
Requires-Dist: pybedtools (>=0.9.0,<0.10.0)
Requires-Dist: pyranges (>=0.0.120,<0.0.121)
Requires-Dist: pysam (>=0.21.0,<0.22.0)
Requires-Dist: seqpro (>=0.1.1,<0.2.0)
Requires-Dist: torch[torch] (>=2) ; extra == "torch"
Requires-Dist: tqdm (>=4.65.0,<5.0.0)
Requires-Dist: typing-extensions (>=4.5.0,<5.0.0)
Requires-Dist: xarray (>=2023.10.0)
Requires-Dist: zarr (>=2.14.2,<3.0.0)
